tensorneko_lib-0.3.22.dist-info/METADATA
tensorneko_lib-0.3.22.dist-info/WHEEL
tensorneko_lib-0.3.22.dist-info/licenses/LICENSE
tensorneko_lib/__init__.py
tensorneko_lib/tensorneko_lib.pypy38-pp73-s390x-linux-gnu.so
tensorneko_lib-0.3.22.dist-info/RECORD
