Metadata-Version: 2.4
Name: tensorneko_lib
Version: 0.3.22
Classifier: Programming Language :: Rust
Classifier: Programming Language :: Python :: Implementation :: CPython
Classifier: Programming Language :: Python :: 3
Classifier: Programming Language :: Python :: 3.7
Classifier: Programming Language :: Python :: 3.8
Classifier: Programming Language :: Python :: 3.9
Classifier: Programming Language :: Python :: 3.10
Classifier: Programming Language :: Python :: 3.11
Classifier: Programming Language :: Python :: 3.12
Classifier: Programming Language :: Python :: 3.13
Classifier: License :: OSI Approved :: MIT License
Classifier: Operating System :: OS Independent
Classifier: Intended Audience :: Developers
Classifier: Topic :: Scientific/Engineering :: Artificial Intelligence
Classifier: Topic :: Utilities
License-File: LICENSE
Keywords: pytorch,AI
Author-email: ControlNet <smczx@hotmail.com>
Requires-Python: >=3.7
Project-URL: Homepage, https://github.com/ControlNet/tensorneko
Project-URL: Source Code, https://github.com/ControlNet/tensorneko
Project-URL: Bug Tracker, https://github.com/ControlNet/tensorneko/issues
